{
  "main": {
    "id": "b8388a8ab7535854",
    "type": "split",
    "children": [
      {
        "id": "30329f3e15dd0ff7",
        "type": "tabs",
        "children": [
          {
            "id": "fdbf542333b046b0",
            "type": "leaf",
            "state": {
              "type": "empty",
              "state": {},
              "icon": "lucide-file",
              "title": "Nueva pestaña"
            }
          },
          {
            "id": "5f849ded0ef9dc22",
            "type": "leaf",
            "state": {
              "type": "markdown",
              "state": {
                "file": "Reportes/Reportes_criticos/Reportes criticos.md",
                "mode": "source",
                "source": false
              },
              "icon": "lucide-file",
              "title": "Reportes criticos"
            }
          }
        ],
        "currentTab": 1
      }
    ],
    "direction": "vertical"
  },
  "left": {
    "id": "d79b9f805c179a0d",
    "type": "split",
    "children": [
      {
        "id": "b81962483c219aae",
        "type": "tabs",
        "children": [
          {
            "id": "69794ff9b04fecef",
            "type": "leaf",
            "state": {
              "type": "file-explorer",
              "state": {
                "sortOrder": "alphabetical",
                "autoReveal": false
              },
              "icon": "lucide-folder-closed",
              "title": "Explorador de archivos"
            }
          },
          {
            "id": "c186236435a3a3ba",
            "type": "leaf",
            "state": {
              "type": "search",
              "state": {
                "query": "",
                "matchingCase": false,
                "explainSearch": false,
                "collapseAll": false,
                "extraContext": false,
                "sortOrder": "alphabetical"
              },
              "icon": "lucide-search",
              "title": "Buscar"
            }
          },
          {
            "id": "49d94074a6fa5ef7",
            "type": "leaf",
            "state": {
              "type": "bookmarks",
              "state": {},
              "icon": "lucide-bookmark",
              "title": "Bookmarks"
            }
          }
        ]
      }
    ],
    "direction": "horizontal",
    "width": 200
  },
  "right": {
    "id": "0e3eda528a7c121e",
    "type": "split",
    "children": [
      {
        "id": "e73d09783ebc648d",
        "type": "tabs",
        "children": [
          {
            "id": "ff4f2f927c948a9c",
            "type": "leaf",
            "state": {
              "type": "backlink",
              "state": {
                "file": "Welcome.md",
                "collapseAll": false,
                "extraContext": false,
                "sortOrder": "alphabetical",
                "showSearch": false,
                "searchQuery": "",
                "backlinkCollapsed": false,
                "unlinkedCollapsed": true
              },
              "icon": "links-coming-in",
              "title": "Backlinks for Welcome"
            }
          },
          {
            "id": "3e6aa85675a2cbec",
            "type": "leaf",
            "state": {
              "type": "outgoing-link",
              "state": {
                "file": "Welcome.md",
                "linksCollapsed": false,
                "unlinkedCollapsed": true
              },
              "icon": "links-going-out",
              "title": "Outgoing links from Welcome"
            }
          },
          {
            "id": "fc1697c87ec18a8f",
            "type": "leaf",
            "state": {
              "type": "tag",
              "state": {
                "sortOrder": "frequency",
                "useHierarchy": true,
                "showSearch": false,
                "searchQuery": ""
              },
              "icon": "lucide-tags",
              "title": "Etiquetas"
            }
          },
          {
            "id": "a657aaf2d550a99f",
            "type": "leaf",
            "state": {
              "type": "outline",
              "state": {
                "file": "ORACLE APEX.md",
                "followCursor": false,
                "showSearch": false,
                "searchQuery": ""
              },
              "icon": "lucide-list",
              "title": "Esquema de ORACLE APEX"
            }
          },
          {
            "id": "0f406eb22c444e34",
            "type": "leaf",
            "state": {
              "type": "mermaid-toolbar-view",
              "state": {},
              "icon": "lucide-file",
              "title": "Complemento no activo"
            }
          }
        ],
        "currentTab": 3
      }
    ],
    "direction": "horizontal",
    "width": 200,
    "collapsed": true
  },
  "left-ribbon": {
    "hiddenItems": {
      "switcher:Abrir selector rápido": false,
      "graph:Abrir vista gráfica": false,
      "canvas:Crear nuevo lienzo": false,
      "daily-notes:Abrir la nota de hoy": false,
      "templates:Insertar plantilla": false,
      "command-palette:Abrir paleta de comandos": false,
      "audio-recorder:Iniciar/Detener la grabación": false,
      "mermaid-tools:Open Mermaid Toolbar": false
    }
  },
  "active": "5f849ded0ef9dc22",
  "lastOpenFiles": [
    "Reportes/Plantilla Reportes.md",
    "Infraestructura/Index de Servidores.md",
    "Infraestructura/Clasificación de Prioridades para Servidores.md",
    "Infraestructura/Ficha Técnica Servidores.md",
    "Procesos/Ficha Tecnicas Procesos/Ficha Técnica Tipos de Cambio Intranet.md",
    "Procesos/Ficha Tecnicas Procesos/Ficha Técnica H2H Cuentas por pagar.md",
    "Procesos/Ficha Tecnicas Procesos/Ficha Técnica Evento Corn Colloquium.md",
    "Procesos/Ficha Tecnicas Procesos/Ficha Técnica Especificaciones Cliente (SF).md",
    "Procesos/Ficha Tecnicas Procesos/Ficha Técnica de Facturacion.md",
    "Procesos/Ficha Tecnicas Procesos/Ficha Técnica Concur.md",
    "Procesos/Ficha Tecnicas Procesos/Ficha Técnica Certificados de Calidad Legados.md",
    "Procesos/Ficha Tecnicas Procesos/Ficha Técnica Bascula.md",
    "Procesos/Ficha Tecnicas Procesos/Ficha Técnica Almacenamiento de archivos.md",
    "Procesos/Ficha Tecnicas Procesos/Ficha Técnica H2H Tesorería.md",
    "README.md",
    "Objetivos.md",
    "Cumplimiento CMMI - APPS.md",
    "Reportes/Reportes_criticos/Reportes criticos.md",
    "Guia de Reportes Oracle BI/Módulos y Objetivos de Reportes.md",
    "Guia de Reportes Oracle BI/INDEX REPORTES CRITICOS.md",
    "Guia de Reportes Oracle BI/Identificar Tipos Reporte.md",
    "Guia de Reportes Oracle BI/Creacion de Plantilla y Query.md",
    "Guia de Reportes Oracle BI/Oracle.md",
    "Guia de Reportes Oracle BI/ORACLE APEX.md",
    "Guia de Reportes Oracle BI/Tablas Principales.md",
    "Guia de Reportes Oracle BI/ss/Pasted image 20250522093605.png",
    "Guia de Reportes Oracle BI/ss/Pasted image 20250522083056.png",
    "Guia de Reportes Oracle BI/ss",
    "Infraestructura/Fichas Tecnicas Infraestructura/Ficha técnica de dcamxpvm01 (productivo).md",
    "Guia de Reportes Oracle BI/ss/Pasted image 20250522090555.png",
    "Guia de Reportes Oracle BI/ss/Pasted image 20250522083755.png",
    "Guia de Reportes Oracle BI/ss/Pasted image 20250522083552.png",
    "Pasted image 20250522081251.png",
    "Guia de Reportes Oracle BI",
    "Reportes/Reportes_criticos",
    "Reportes",
    "Pasted image 20250505123618.jpg",
    "Pasted image 20250505085906.png",
    "Infraestructura/Fichas Tecnicas Infraestructura/lista.txt",
    "Application/Fichas Tecnicas Aplicaciones/lista.txt",
    "Infraestructura/Fichas Tecnicas Infraestructura",
    "Procesos/Ficha Tecnicas Procesos",
    "Procesos",
    "Application/Fichas Tecnicas Aplicaciones"
  ]
}